async_blp/__init__.py
async_blp/async_blp.py
async_blp/base_handler.py
async_blp/base_request.py
async_blp/enums.py
async_blp/errors.py
async_blp/handlers.py
async_blp/instruments_requests.py
async_blp/parser.py
async_blp/requests.py
async_blp/utils/__init__.py
async_blp/utils/blp_name.py
async_blp/utils/env_test.py
async_blp/utils/exc.py
async_blp/utils/log.py
async_blp/utils/misc.py
async_blp-0.0.1.dist-info/LICENSE
async_blp-0.0.1.dist-info/METADATA
async_blp-0.0.1.dist-info/WHEEL
async_blp-0.0.1.dist-info/top_level.txt
async_blp-0.0.1.dist-info/RECORD
