Metadata-Version: 2.1
Name: async-blp
Version: 0.0.1
Summary: Async wrapper for Bloomberg Open API
Home-page: https://github.com/rockscie/async_blp
Author: Rocksci
License: MIT
Platform: any
Classifier: Programming Language :: Python :: 3.7
Classifier: License :: OSI Approved :: MIT License
Classifier: Operating System :: OS Independent
Classifier: Development Status :: 3 - Alpha
Classifier: Intended Audience :: Developers
Classifier: Intended Audience :: Financial and Insurance Industry
Classifier: Topic :: Office/Business :: Financial
Requires-Dist: pandas (>=0.20.0)
